LICENSE.txt
MANIFEST.in
README.rst
pyhp.py
requirements.txt
setup.py
pyhp.egg-info/PKG-INFO
pyhp.egg-info/SOURCES.txt
pyhp.egg-info/dependency_links.txt
pyhp.egg-info/requires.txt
pyhp.egg-info/top_level.txt
scripts/pyhp