Metadata-Version: 1.0
Name: pyhp
Version: 0.1
Summary: a simple tool to hit websites at a given interval and display whether they are up or not
Home-page: https://github.com/radiosilence/pyhp
Author: James Cleveland
Author-email: jamescleveland@gmail.com
License: LICENSE.txt
Platform: UNKNOWN
